<?xml version="1.0" encoding="UTF-8" ?>
<!DOCTYPE mapper PUBLIC "-//mybatis.org//DTD Mapper 3.0//EN" "http://mybatis.org/dtd/mybatis-3-mapper.dtd" >
<mapper namespace="com.limited.app.db.dao.TemplatedetailsMapper" >
  <resultMap id="BaseResultMap" type="com.limited.app.bean.Templatedetails" >
    <!--
      WARNING - @mbggenerated
      This element is automatically generated by MyBatis Generator, do not modify.
      This element was generated on Thu Mar 31 22:43:17 EDT 2011.
    -->
    <id column="id" property="id" jdbcType="INTEGER" />
    <result column="templateid" property="templateid" jdbcType="INTEGER" />
    <result column="alloctypeid" property="alloctypeid" jdbcType="INTEGER" />
    <result column="secid" property="secid" jdbcType="INTEGER" />
    <result column="indid" property="indid" jdbcType="INTEGER" />
    <result column="interid" property="interid" jdbcType="INTEGER" />
    <result column="prct" property="prct" jdbcType="DECIMAL" />
  </resultMap>
  <sql id="Example_Where_Clause" >
    <!--
      WARNING - @mbggenerated
      This element is automatically generated by MyBatis Generator, do not modify.
      This element was generated on Thu Mar 31 22:43:17 EDT 2011.
    -->
    <where >
      <foreach collection="oredCriteria" item="criteria" separator="or" >
        <if test="criteria.valid" >
          <trim prefix="(" suffix=")" prefixOverrides="and" >
            <foreach collection="criteria.criteria" item="criterion" >
              <choose >
                <when test="criterion.noValue" >
                  and ${criterion.condition}
                </when>
                <when test="criterion.singleValue" >
                  and ${criterion.condition} #{criterion.value}
                </when>
                <when test="criterion.betweenValue" >
                  and ${criterion.condition} #{criterion.value} and #{criterion.secondValue}
                </when>
                <when test="criterion.listValue" >
                  and ${criterion.condition}
                  <foreach collection="criterion.value" item="listItem" open="(" close=")" separator="," >
                    #{listItem}
                  </foreach>
                </when>
              </choose>
            </foreach>
          </trim>
        </if>
      </foreach>
    </where>
  </sql>
  <sql id="Update_By_Example_Where_Clause" >
    <!--
      WARNING - @mbggenerated
      This element is automatically generated by MyBatis Generator, do not modify.
      This element was generated on Thu Mar 31 22:43:17 EDT 2011.
    -->
    <where >
      <foreach collection="example.oredCriteria" item="criteria" separator="or" >
        <if test="criteria.valid" >
          <trim prefix="(" suffix=")" prefixOverrides="and" >
            <foreach collection="criteria.criteria" item="criterion" >
              <choose >
                <when test="criterion.noValue" >
                  and ${criterion.condition}
                </when>
                <when test="criterion.singleValue" >
                  and ${criterion.condition} #{criterion.value}
                </when>
                <when test="criterion.betweenValue" >
                  and ${criterion.condition} #{criterion.value} and #{criterion.secondValue}
                </when>
                <when test="criterion.listValue" >
                  and ${criterion.condition}
                  <foreach collection="criterion.value" item="listItem" open="(" close=")" separator="," >
                    #{listItem}
                  </foreach>
                </when>
              </choose>
            </foreach>
          </trim>
        </if>
      </foreach>
    </where>
  </sql>
  <sql id="Base_Column_List" >
    <!--
      WARNING - @mbggenerated
      This element is automatically generated by MyBatis Generator, do not modify.
      This element was generated on Thu Mar 31 22:43:17 EDT 2011.
    -->
    id, templateid, alloctypeid, secid, indid, interid, prct
  </sql>
  <select id="selectByExample" resultMap="BaseResultMap" parameterType="com.limited.app.bean.TemplatedetailsExample" >
    <!--
      WARNING - @mbggenerated
      This element is automatically generated by MyBatis Generator, do not modify.
      This element was generated on Thu Mar 31 22:43:17 EDT 2011.
    -->
    select
    <if test="distinct" >
      distinct
    </if>
    <include refid="Base_Column_List" />
    from templatedetails
    <if test="_parameter != null" >
      <include refid="Example_Where_Clause" />
    </if>
    <if test="orderByClause != null" >
      order by ${orderByClause}
    </if>
  </select>
  <select id="selectByPrimaryKey" resultMap="BaseResultMap" parameterType="java.lang.Integer" >
    <!--
      WARNING - @mbggenerated
      This element is automatically generated by MyBatis Generator, do not modify.
      This element was generated on Thu Mar 31 22:43:17 EDT 2011.
    -->
    select 
    <include refid="Base_Column_List" />
    from templatedetails
    where id = #{id,jdbcType=INTEGER}
  </select>
  <delete id="deleteByPrimaryKey" parameterType="java.lang.Integer" >
    <!--
      WARNING - @mbggenerated
      This element is automatically generated by MyBatis Generator, do not modify.
      This element was generated on Thu Mar 31 22:43:17 EDT 2011.
    -->
    delete from templatedetails
    where id = #{id,jdbcType=INTEGER}
  </delete>
  <delete id="deleteByExample" parameterType="com.limited.app.bean.TemplatedetailsExample" >
    <!--
      WARNING - @mbggenerated
      This element is automatically generated by MyBatis Generator, do not modify.
      This element was generated on Thu Mar 31 22:43:17 EDT 2011.
    -->
    delete from templatedetails
    <if test="_parameter != null" >
      <include refid="Example_Where_Clause" />
    </if>
  </delete>
  <insert id="insert" parameterType="com.limited.app.bean.Templatedetails" >
    <!--
      WARNING - @mbggenerated
      This element is automatically generated by MyBatis Generator, do not modify.
      This element was generated on Thu Mar 31 22:43:17 EDT 2011.
    -->
    <selectKey resultType="java.lang.Integer" keyProperty="id" order="AFTER" >
      SELECT SCOPE_IDENTITY()
    </selectKey>
    insert into templatedetails (templateid, alloctypeid, secid, 
      indid, interid, prct
      )
    values (#{templateid,jdbcType=INTEGER}, #{alloctypeid,jdbcType=INTEGER}, #{secid,jdbcType=INTEGER}, 
      #{indid,jdbcType=INTEGER}, #{interid,jdbcType=INTEGER}, #{prct,jdbcType=DECIMAL}
      )
  </insert>
  <insert id="insertSelective" parameterType="com.limited.app.bean.Templatedetails" >
    <!--
      WARNING - @mbggenerated
      This element is automatically generated by MyBatis Generator, do not modify.
      This element was generated on Thu Mar 31 22:43:17 EDT 2011.
    -->
    <selectKey resultType="java.lang.Integer" keyProperty="id" order="AFTER" >
      SELECT SCOPE_IDENTITY()
    </selectKey>
    insert into templatedetails
    <trim prefix="(" suffix=")" suffixOverrides="," >
      <if test="templateid != null" >
        templateid,
      </if>
      <if test="alloctypeid != null" >
        alloctypeid,
      </if>
      <if test="secid != null" >
        secid,
      </if>
      <if test="indid != null" >
        indid,
      </if>
      <if test="interid != null" >
        interid,
      </if>
      <if test="prct != null" >
        prct,
      </if>
    </trim>
    <trim prefix="values (" suffix=")" suffixOverrides="," >
      <if test="templateid != null" >
        #{templateid,jdbcType=INTEGER},
      </if>
      <if test="alloctypeid != null" >
        #{alloctypeid,jdbcType=INTEGER},
      </if>
      <if test="secid != null" >
        #{secid,jdbcType=INTEGER},
      </if>
      <if test="indid != null" >
        #{indid,jdbcType=INTEGER},
      </if>
      <if test="interid != null" >
        #{interid,jdbcType=INTEGER},
      </if>
      <if test="prct != null" >
        #{prct,jdbcType=DECIMAL},
      </if>
    </trim>
  </insert>
  <select id="countByExample" parameterType="com.limited.app.bean.TemplatedetailsExample" resultType="java.lang.Integer" >
    <!--
      WARNING - @mbggenerated
      This element is automatically generated by MyBatis Generator, do not modify.
      This element was generated on Thu Mar 31 22:43:17 EDT 2011.
    -->
    select count(*) from templatedetails
    <if test="_parameter != null" >
      <include refid="Example_Where_Clause" />
    </if>
  </select>
  <update id="updateByExampleSelective" parameterType="map" >
    <!--
      WARNING - @mbggenerated
      This element is automatically generated by MyBatis Generator, do not modify.
      This element was generated on Thu Mar 31 22:43:17 EDT 2011.
    -->
    update templatedetails
    <set >
      <if test="record.id != null" >
        id = #{record.id,jdbcType=INTEGER},
      </if>
      <if test="record.templateid != null" >
        templateid = #{record.templateid,jdbcType=INTEGER},
      </if>
      <if test="record.alloctypeid != null" >
        alloctypeid = #{record.alloctypeid,jdbcType=INTEGER},
      </if>
      <if test="record.secid != null" >
        secid = #{record.secid,jdbcType=INTEGER},
      </if>
      <if test="record.indid != null" >
        indid = #{record.indid,jdbcType=INTEGER},
      </if>
      <if test="record.interid != null" >
        interid = #{record.interid,jdbcType=INTEGER},
      </if>
      <if test="record.prct != null" >
        prct = #{record.prct,jdbcType=DECIMAL},
      </if>
    </set>
    <if test="_parameter != null" >
      <include refid="Update_By_Example_Where_Clause" />
    </if>
  </update>
  <update id="updateByExample" parameterType="map" >
    <!--
      WARNING - @mbggenerated
      This element is automatically generated by MyBatis Generator, do not modify.
      This element was generated on Thu Mar 31 22:43:17 EDT 2011.
    -->
    update templatedetails
    set id = #{record.id,jdbcType=INTEGER},
      templateid = #{record.templateid,jdbcType=INTEGER},
      alloctypeid = #{record.alloctypeid,jdbcType=INTEGER},
      secid = #{record.secid,jdbcType=INTEGER},
      indid = #{record.indid,jdbcType=INTEGER},
      interid = #{record.interid,jdbcType=INTEGER},
      prct = #{record.prct,jdbcType=DECIMAL}
    <if test="_parameter != null" >
      <include refid="Update_By_Example_Where_Clause" />
    </if>
  </update>
  <update id="updateByPrimaryKeySelective" parameterType="com.limited.app.bean.Templatedetails" >
    <!--
      WARNING - @mbggenerated
      This element is automatically generated by MyBatis Generator, do not modify.
      This element was generated on Thu Mar 31 22:43:17 EDT 2011.
    -->
    update templatedetails
    <set >
      <if test="templateid != null" >
        templateid = #{templateid,jdbcType=INTEGER},
      </if>
      <if test="alloctypeid != null" >
        alloctypeid = #{alloctypeid,jdbcType=INTEGER},
      </if>
      <if test="secid != null" >
        secid = #{secid,jdbcType=INTEGER},
      </if>
      <if test="indid != null" >
        indid = #{indid,jdbcType=INTEGER},
      </if>
      <if test="interid != null" >
        interid = #{interid,jdbcType=INTEGER},
      </if>
      <if test="prct != null" >
        prct = #{prct,jdbcType=DECIMAL},
      </if>
    </set>
    where id = #{id,jdbcType=INTEGER}
  </update>
  <update id="updateByPrimaryKey" parameterType="com.limited.app.bean.Templatedetails" >
    <!--
      WARNING - @mbggenerated
      This element is automatically generated by MyBatis Generator, do not modify.
      This element was generated on Thu Mar 31 22:43:17 EDT 2011.
    -->
    update templatedetails
    set templateid = #{templateid,jdbcType=INTEGER},
      alloctypeid = #{alloctypeid,jdbcType=INTEGER},
      secid = #{secid,jdbcType=INTEGER},
      indid = #{indid,jdbcType=INTEGER},
      interid = #{interid,jdbcType=INTEGER},
      prct = #{prct,jdbcType=DECIMAL}
    where id = #{id,jdbcType=INTEGER}
  </update>
</mapper>